geekbot_cli/__init__.py
geekbot_cli/api_client.py
geekbot_cli/cli.py
geekbot_cli/config_manager.py
geekbot_cli/exceptions.py
geekbot_cli/main.py
geekbot_cli/models.py
geekbot_cli-0.1.4.dist-info/LICENSE
geekbot_cli-0.1.4.dist-info/METADATA
geekbot_cli-0.1.4.dist-info/WHEEL
geekbot_cli-0.1.4.dist-info/entry_points.txt
geekbot_cli-0.1.4.dist-info/top_level.txt
geekbot_cli-0.1.4.dist-info/RECORD
