Metadata-Version: 2.1
Name: geekbot_cli
Version: 0.1.4
Summary: Interact with Geekbot through terminal
Home-page: https://github.com/geekbot-com/geekbot-cli
Author: The Geekbot team
Author-email: hey@geekbot.io
License: MIT
Keywords: geekbot standup workflow
License-File: LICENSE
Requires-Dist: click ==7.1.2
Requires-Dist: requests ==2.25.1
Requires-Dist: rich ==9.13.0
Requires-Dist: prompt-toolkit ==3.0.18
Requires-Dist: keyring ==24.3.0
Requires-Dist: coverage
